aspose_cad_cloud-24.5.2.data/data/LICENSE
asposecadcloud/__init__.py
asposecadcloud/api_client.py
asposecadcloud/configuration.py
asposecadcloud/rest.py
asposecadcloud/api/__init__.py
asposecadcloud/api/cad_api.py
asposecadcloud/models/__init__.py
asposecadcloud/models/bitmap_compression.py
asposecadcloud/models/bmp_options_dto.py
asposecadcloud/models/cad_draw_type_mode.py
asposecadcloud/models/cad_rasterization_options_dto.py
asposecadcloud/models/cad_response.py
asposecadcloud/models/cf2_properties.py
asposecadcloud/models/cgm_options_dto.py
asposecadcloud/models/color_dto.py
asposecadcloud/models/color_modes.py
asposecadcloud/models/compression_method.py
asposecadcloud/models/dgn_properties.py
asposecadcloud/models/dicom_options_dto.py
asposecadcloud/models/disc_usage.py
asposecadcloud/models/draco_options_dto.py
asposecadcloud/models/drawing_options_base_dto.py
asposecadcloud/models/dwf_options_dto.py
asposecadcloud/models/dwf_properties.py
asposecadcloud/models/dwg_properties.py
asposecadcloud/models/dxf_options_dto.py
asposecadcloud/models/dxf_properties.py
asposecadcloud/models/error.py
asposecadcloud/models/error_details.py
asposecadcloud/models/fbx_options_dto.py
asposecadcloud/models/fbx_properties.py
asposecadcloud/models/file_version.py
asposecadcloud/models/file_versions.py
asposecadcloud/models/files_list.py
asposecadcloud/models/files_upload_result.py
asposecadcloud/models/gif_options_dto.py
asposecadcloud/models/glb_options_dto.py
asposecadcloud/models/gltf_options_dto.py
asposecadcloud/models/graphics_options.py
asposecadcloud/models/ifc_properties.py
asposecadcloud/models/igs_properties.py
asposecadcloud/models/interpolation_mode.py
asposecadcloud/models/jpeg2000_codec.py
asposecadcloud/models/jpeg2000_options_dto.py
asposecadcloud/models/jpeg_compression_color_mode.py
asposecadcloud/models/jpeg_compression_mode.py
asposecadcloud/models/jpeg_options_dto.py
asposecadcloud/models/line_cap.py
asposecadcloud/models/obj_options_dto.py
aspose_cad_cloud-24.5.2.dist-info/LICENSE
aspose_cad_cloud-24.5.2.dist-info/METADATA
aspose_cad_cloud-24.5.2.dist-info/WHEEL
aspose_cad_cloud-24.5.2.dist-info/top_level.txt
aspose_cad_cloud-24.5.2.dist-info/RECORD
