Metadata-Version: 2.1
Name: aspose-cad-cloud
Version: 24.5.2
Summary: Aspose.CAD Cloud Python SDK
Home-page: https://products.aspose.cloud/cad
Author: Aspose
Author-email: vitalii.kornyliuk@aspose.com
License: MIT
Keywords: Aspose,CAD,Cloud,REST,API,SDK,drawing,watermark,DWG,DXF,DWF,DWFX,DWT,STL,IGS,DGN,OBJ,CF2,GLB,GLTF,CGM,U3D,3DSimage,bmp,gif,jpg,jpeg,jpeg2000,jp2,j2k,png,psd,tiff,tif,wmf,svg,export,conversion
Platform: UNKNOWN
Classifier: Development Status :: 5 - Production/Stable
Classifier: Intended Audience :: Developers
Classifier: Topic :: Multimedia :: Graphics
Classifier: License :: OSI Approved :: MIT License
Classifier: Programming Language :: Python :: 2
Classifier: Programming Language :: Python :: 2.7
Classifier: Programming Language :: Python :: 3
Classifier: Programming Language :: Python :: 3.1
Classifier: Programming Language :: Python :: 3.2
Classifier: Programming Language :: Python :: 3.3
Classifier: Programming Language :: Python :: 3.4
Classifier: Programming Language :: Python :: 3.5
Classifier: Programming Language :: Python :: 3.6
Classifier: Programming Language :: Python :: 3.7
Classifier: Programming Language :: Python :: 3.8
Classifier: Programming Language :: Python :: 3.9
Classifier: Programming Language :: Python :: 3.10
Classifier: Programming Language :: Python :: 3.11
Classifier: Programming Language :: Python :: 3.12
Requires-Dist: certifi (>=2018.1)
Requires-Dist: python-dateutil (>=2.8)
Requires-Dist: six (>=1.11)
Requires-Dist: urllib3 (>=1.22)
